{
    "score1c": "node1",
    "score1b": "node2",
    "score4a": "node3",
    "master": "node4",
    "score2b": "node8",
    "score3b": "node10",
    "score2c": "node11",
    "score3c": "node12",
    "resnet8": "node13",
    "storeclass3": "node13",
    "storeclass2": "node13",
    "storeclass5": "node13",
    "storeclass7": "node13",
    "storeclass6": "node13",
    "storeclass8": "node13",
    "storeclass4": "node13",
    "storeclass1": "node13",
    "lccenc2": "node13",
    "lccenc7": "node13",
    "lccenc6": "node13",
    "score3a": "node15",
    "preagg8": "node15",
    "lccdec8": "node15",
    "preagg3": "node15",
    "lccdec3": "node15",
    "score7b": "node17",
    "preagg4": "node17",
    "lccdec4": "node17",
    "preagg2": "node17",
    "lccdec2": "node17",
    "resnet2": "node18",
    "score8a": "node20",
    "score6a": "node21",
    "preagg5": "node23",
    "lccdec5": "node23",
    "resnet6": "node25",
    "resnet0": "node26",
    "score7c": "node27",
    "score7a": "node28",
    "score2a": "node29",
    "preagg7": "node29",
    "lccdec7": "node29",
    "score5a": "node30",
    "lccenc1": "node31",
    "resnet5": "node34",
    "lccenc3": "node34",
    "lccenc8": "node34",
    "lccenc4": "node34",
    "lccenc5": "node34",
    "score1a": "node35",
    "preagg1": "node35",
    "lccdec1": "node35",
    "score4c": "node38",
    "resnet1": "node40",
    "score8b": "node45",
    "resnet3": "node50",
    "score5c": "node52",
    "collage": "node52",
    "score8c": "node53",
    "score6c": "node58",
    "preagg6": "node60",
    "lccdec6": "node60",
    "score4b": "node61",
    "score5b": "node63",
    "score6b": "node67",
    "resnet4": "node72",
    "resnet7": "node75"
}